odoo_log_parser/__init__.py
odoo_log_parser/odoo_log_parser.py
odoo_log_parser/odoo_test_digest.py
odoologparser-0.2.0.data/scripts/Odoo-LogParser.py
odoologparser-0.2.0.dist-info/licenses/LICENSE
odoologparser-0.2.0.dist-info/METADATA
odoologparser-0.2.0.dist-info/WHEEL
odoologparser-0.2.0.dist-info/top_level.txt
odoologparser-0.2.0.dist-info/RECORD
