Metadata-Version: 2.4
Name: OdooLogParser
Version: 0.2.0
Summary: Log Parser for Odoo logs, including a test digest generator
Author-email: João Jerónimo <joao.jeronimo.pro@gmail.com>
Classifier: Development Status :: 5 - Production/Stable
Requires-Python: >=3.7
License-File: LICENSE
Dynamic: license-file
